pepdbagent/__init__.py
pepdbagent/_version.py
pepdbagent/const.py
pepdbagent/db_utils.py
pepdbagent/exceptions.py
pepdbagent/models.py
pepdbagent/pepdbagent.py
pepdbagent/utils.py
pepdbagent/alembic/README
pepdbagent/alembic/__init__.py
pepdbagent/alembic/env.py
pepdbagent/alembic/script.py.mako
pepdbagent/alembic/versions/44cb1e7a80de_initial_migration.py
pepdbagent/alembic/versions/8a037f13b4e5_upgrading_schemas.py
pepdbagent/alembic/versions/__init__.py
pepdbagent/modules/__init__.py
pepdbagent/modules/annotation.py
pepdbagent/modules/namespace.py
pepdbagent/modules/project.py
pepdbagent/modules/sample.py
pepdbagent/modules/schema.py
pepdbagent/modules/user.py
pepdbagent/modules/view.py
pepdbagent-0.12.3.dist-info/licenses/LICENSE.txt
tests/__init__.py
tests/conftest.py
tests/test_annotation.py
tests/test_namespace.py
tests/test_project.py
tests/test_project_history.py
tests/test_samples.py
tests/test_schema.py
tests/test_tar_meta.py
tests/test_updates.py
tests/test_views.py
tests/utils.py
pepdbagent-0.12.3.dist-info/METADATA
pepdbagent-0.12.3.dist-info/WHEEL
pepdbagent-0.12.3.dist-info/top_level.txt
pepdbagent-0.12.3.dist-info/RECORD
