Metadata-Version: 2.4
Name: pepdbagent
Version: 0.12.3
Summary: A python-based database manager for portable encapsulated projects
Home-page: https://github.com/pepkit/pepdbagent/
Author: Oleksandr Khoroshevskyi <khorosh@virginia.edu>
License: BSD2
Keywords: project,metadata,bioinformatics,database
Classifier: Development Status :: 4 - Beta
Classifier: License :: OSI Approved :: BSD License
Classifier: Programming Language :: Python :: 3.8
Classifier: Programming Language :: Python :: 3.9
Classifier: Programming Language :: Python :: 3.10
Classifier: Programming Language :: Python :: 3.11
Classifier: Programming Language :: Python :: 3.12
Classifier: Topic :: Scientific/Engineering :: Bio-Informatics
License-File: LICENSE.txt
Requires-Dist: sqlalchemy>=2.0.0
Requires-Dist: logmuse>=0.2.7
Requires-Dist: peppy>=0.40.6
Requires-Dist: ubiquerg>=0.6.2
Requires-Dist: coloredlogs>=15.0.1
Requires-Dist: pytest-mock
Requires-Dist: pydantic>=2.0
Requires-Dist: psycopg>=3.1.15
Requires-Dist: numpy>=1.24.4
Requires-Dist: alembic>=1.15.1
Dynamic: author
Dynamic: classifier
Dynamic: description
Dynamic: description-content-type
Dynamic: home-page
Dynamic: keywords
Dynamic: license
Dynamic: license-file
Dynamic: requires-dist
Dynamic: summary
